[
  {
    "image":
      "https://d1nhio0ox7pgb.cloudfront.net/_img/o_collection_png/green_dark_grey/256x256/plain/user.png",
    "header": "Sam Smith",
    "meta": "Chief Executive officer",
    "mail": "sam.smith@rdp.com"
  },
  {
    "image":
      "https://d1nhio0ox7pgb.cloudfront.net/_img/o_collection_png/green_dark_grey/256x256/plain/user.png",
    "header": "Jane Doe",
    "meta": "Head of Marketing",
    "mail": "jane.doe@rdp.com"
  },
  {
    "image":
      "https://d1nhio0ox7pgb.cloudfront.net/_img/o_collection_png/green_dark_grey/256x256/plain/user.png",
    "header": "Steve King",
    "meta": "Head of Sales",
    "mail": "steve.king@rdp.com"
  },
  {
    "image":
      "https://d1nhio0ox7pgb.cloudfront.net/_img/o_collection_png/green_dark_grey/256x256/plain/user.png",
    "header": "John Doe",
    "meta": "Head of Production",
    "mail": "john.doe@rdp.com"
  },
  {
    "image":
      "https://d1nhio0ox7pgb.cloudfront.net/_img/o_collection_png/green_dark_grey/256x256/plain/user.png",
    "header": "Eric Johnson",
    "meta": "Head of IT",
    "mail": "eric.johnson@rdp.com"
  }
]
